{
  "headers": {
    "serverProducts": [
      {
        "defaults": {
          "category": "Web 服务器"
        },
        "rules": [
          {
            "name": "Nginx",
            "patterns": [
              "nginx"
            ]
          },
          {
            "name": "OpenResty",
            "patterns": [
              "openresty"
            ]
          },
          {
            "name": "Tengine",
            "patterns": [
              "tengine"
            ]
          },
          {
            "name": "Apache HTTP Server",
            "patterns": [
              "apache"
            ]
          },
          {
            "name": "Microsoft IIS",
            "patterns": [
              "microsoft-iis|iis"
            ]
          },
          {
            "name": "LiteSpeed",
            "patterns": [
              "litespeed"
            ]
          },
          {
            "name": "Caddy",
            "patterns": [
              "caddy"
            ]
          },
          {
            "name": "Envoy",
            "patterns": [
              "envoy"
            ]
          },
          {
            "name": "Traefik",
            "patterns": [
              "traefik"
            ]
          },
          {
            "name": "HAProxy",
            "patterns": [
              "haproxy"
            ]
          },
          {
            "name": "Varnish",
            "patterns": [
              "varnish"
            ]
          },
          {
            "name": "Apache Traffic Server",
            "patterns": [
              "trafficserver|ats"
            ]
          },
          {
            "name": "Jetty",
            "patterns": [
              "jetty"
            ]
          },
          {
            "name": "Tomcat",
            "patterns": [
              "tomcat"
            ]
          },
          {
            "name": "Undertow",
            "patterns": [
              "undertow"
            ]
          },
          {
            "name": "WildFly",
            "patterns": [
              "wildfly"
            ]
          },
          {
            "name": "GlassFish",
            "patterns": [
              "glassfish"
            ]
          },
          {
            "name": "WebSphere",
            "patterns": [
              "websphere"
            ]
          },
          {
            "name": "WebLogic",
            "patterns": [
              "weblogic"
            ]
          },
          {
            "name": "Kestrel",
            "patterns": [
              "kestrel"
            ]
          },
          {
            "name": "Cowboy",
            "patterns": [
              "cowboy"
            ]
          },
          {
            "name": "Puma",
            "patterns": [
              "puma"
            ]
          },
          {
            "name": "Unicorn",
            "patterns": [
              "unicorn"
            ]
          },
          {
            "name": "uWSGI",
            "patterns": [
              "uwsgi"
            ]
          },
          {
            "name": "Gunicorn",
            "patterns": [
              "gunicorn"
            ]
          },
          {
            "name": "Werkzeug",
            "patterns": [
              "werkzeug"
            ]
          }
        ]
      },
      {
        "defaults": {
          "category": "后端 / 服务器框架"
        },
        "rules": [
          {
            "name": "Node.js",
            "patterns": [
              "node\\.?js"
            ]
          },
          {
            "name": "Deno",
            "patterns": [
              "deno"
            ]
          },
          {
            "name": "Bun",
            "patterns": [
              "\\bbun\\b"
            ]
          }
        ]
      },
      {
        "defaults": {
          "category": "CDN / 托管"
        },
        "rules": [
          {
            "name": "Vercel",
            "patterns": [
              "vercel"
            ]
          },
          {
            "name": "Cloudflare",
            "patterns": [
              "cloudflare"
            ]
          },
          {
            "name": "AmazonS3",
            "patterns": [
              "amazons3|amazon s3|s3"
            ]
          },
          {
            "name": "Akamai",
            "patterns": [
              "akamai|ghost"
            ]
          },
          {
            "name": "Fastly",
            "patterns": [
              "fastly"
            ]
          },
          {
            "name": "Bunny CDN",
            "patterns": [
              "bunnycdn|bunny"
            ]
          },
          {
            "name": "Gcore CDN",
            "patterns": [
              "gcore"
            ]
          },
          {
            "name": "Tencent Cloud CDN",
            "patterns": [
              "tencent|qcloud"
            ]
          },
          {
            "name": "Alibaba Cloud CDN",
            "patterns": [
              "aliyun|alibaba|tengine"
            ]
          },
          {
            "name": "Huawei Cloud CDN",
            "patterns": [
              "huawei|hwcdn"
            ]
          },
          {
            "name": "Baidu Cloud CDN",
            "patterns": [
              "baidu|bce"
            ]
          }
        ]
      }
    ]
  }
}
